<annotation>
	<folder>VOC2007</folder>
	<filename>000590.jpg</filename>
	<path>./dataset/round3/train/JPEGImages/000590.jpg</path>
	<source>
		<database>Unknown</database>
	</source>
	<size>
		<width>1000</width>
		<height>800</height>
		<depth>3</depth>
	</size>
	<segmented>0</segmented>
	<object>
		<name>apple</name>
		<pose>Unspecified</pose>
		<truncated>0</truncated>
		<difficult>0</difficult>
		<bndbox>
			<xmin>790</xmin>
			<ymin>518</ymin>
			<xmax>990</xmax>
			<ymax>753</ymax>
		</bndbox>
	</object>
	<object>
		<name>apple</name>
		<pose>Unspecified</pose>
		<truncated>0</truncated>
		<difficult>0</difficult>
		<bndbox>
			<xmin>277</xmin>
			<ymin>448</ymin>
			<xmax>588</xmax>
			<ymax>737</ymax>
		</bndbox>
	</object>
</annotation>