<annotation>
	<folder>VOC2007</folder>
	<filename>001168.jpg</filename>
	<path>./dataset/round3/train/JPEGImages/001168.jpg</path>
	<source>
		<database>Unknown</database>
	</source>
	<size>
		<width>1000</width>
		<height>800</height>
		<depth>3</depth>
	</size>
	<segmented>0</segmented>
	<object>
		<name>apple</name>
		<pose>Unspecified</pose>
		<truncated>0</truncated>
		<difficult>0</difficult>
		<bndbox>
			<xmin>734</xmin>
			<ymin>10</ymin>
			<xmax>990</xmax>
			<ymax>103</ymax>
		</bndbox>
	</object>
	<object>
		<name>apple</name>
		<pose>Unspecified</pose>
		<truncated>0</truncated>
		<difficult>0</difficult>
		<bndbox>
			<xmin>33</xmin>
			<ymin>10</ymin>
			<xmax>235</xmax>
			<ymax>224</ymax>
		</bndbox>
	</object>
	<object>
		<name>apple</name>
		<pose>Unspecified</pose>
		<truncated>0</truncated>
		<difficult>0</difficult>
		<bndbox>
			<xmin>356</xmin>
			<ymin>81</ymin>
			<xmax>601</xmax>
			<ymax>357</ymax>
		</bndbox>
	</object>
	<object>
		<name>apple</name>
		<pose>Unspecified</pose>
		<truncated>0</truncated>
		<difficult>0</difficult>
		<bndbox>
			<xmin>413</xmin>
			<ymin>518</ymin>
			<xmax>649</xmax>
			<ymax>747</ymax>
		</bndbox>
	</object>
	<object>
		<name>apple</name>
		<pose>Unspecified</pose>
		<truncated>0</truncated>
		<difficult>0</difficult>
		<bndbox>
			<xmin>770</xmin>
			<ymin>654</ymin>
			<xmax>964</xmax>
			<ymax>790</ymax>
		</bndbox>
	</object>
</annotation>